{"chunk_definitions":[{"row":36,"row_count":1,"visible":true,"expansion_state":0,"options":{"engine":"r","label":"unnamed-chunk-5"},"document_id":"9127FD84","chunk_id":"cti15d0u5t5x2","chunk_label":"unnamed-chunk-1"},{"row":50,"row_count":1,"visible":true,"expansion_state":0,"options":{"engine":"r","label":"unnamed-chunk-6"},"document_id":"9127FD84","chunk_id":"cr9cm73shvbi7","chunk_label":"unnamed-chunk-2"},{"row":55,"row_count":1,"visible":true,"expansion_state":0,"options":{"engine":"r","label":"unnamed-chunk-7"},"document_id":"9127FD84","chunk_id":"c70l97pb04z6h","chunk_label":"unnamed-chunk-3"},{"row":60,"row_count":1,"visible":true,"expansion_state":0,"options":{"engine":"r","label":"unnamed-chunk-8"},"document_id":"9127FD84","chunk_id":"cw0lrtrjfrzlb","chunk_label":"unnamed-chunk-4"},{"row":65,"row_count":1,"visible":true,"expansion_state":0,"options":{"engine":"r","label":"unnamed-chunk-9"},"document_id":"9127FD84","chunk_id":"cs1q05kwqyks7","chunk_label":"unnamed-chunk-5"},{"row":70,"row_count":1,"visible":true,"expansion_state":0,"options":{"engine":"r","label":"unnamed-chunk-11"},"document_id":"9127FD84","chunk_id":"cxw1wvmv3zpsx","chunk_label":"unnamed-chunk-6"},{"row":86,"row_count":1,"visible":true,"expansion_state":0,"options":{"engine":"r","label":"unnamed-chunk-1"},"document_id":"9127FD84","chunk_id":"cswczq8z9zyzs","chunk_label":"unnamed-chunk-7"},{"row":94,"row_count":1,"visible":true,"expansion_state":0,"options":{"engine":"r","label":"unnamed-chunk-5"},"document_id":"9127FD84","chunk_id":"c35l36wm5715s","chunk_label":"unnamed-chunk-8"},{"row":107,"row_count":1,"visible":true,"expansion_state":0,"options":{"engine":"r","label":"unnamed-chunk-10"},"document_id":"9127FD84","chunk_id":"cz551izghl59t","chunk_label":"unnamed-chunk-9"},{"row":114,"row_count":1,"visible":true,"expansion_state":0,"options":{"engine":"r","label":"unnamed-chunk-12"},"document_id":"9127FD84","chunk_id":"c34jled0ne37s","chunk_label":"unnamed-chunk-10"},{"row":125,"row_count":1,"visible":true,"expansion_state":0,"options":{"engine":"r","label":"unnamed-chunk-31"},"document_id":"9127FD84","chunk_id":"cisb0k9my7j4w","chunk_label":"unnamed-chunk-11"},{"row":133,"row_count":1,"visible":true,"expansion_state":0,"options":{"engine":"r","label":"unnamed-chunk-32"},"document_id":"9127FD84","chunk_id":"csm168lxbd5n8","chunk_label":"unnamed-chunk-12"},{"row":139,"row_count":1,"visible":true,"expansion_state":0,"options":{"engine":"r","label":"unnamed-chunk-34"},"document_id":"9127FD84","chunk_id":"ckendzebyzqxq","chunk_label":"unnamed-chunk-13"},{"row":144,"row_count":1,"visible":true,"expansion_state":0,"options":{"engine":"r","label":"unnamed-chunk-36"},"document_id":"9127FD84","chunk_id":"c5id70bi80b09","chunk_label":"unnamed-chunk-14"},{"row":152,"row_count":1,"visible":true,"expansion_state":0,"options":{"engine":"r","label":"unnamed-chunk-39"},"document_id":"9127FD84","chunk_id":"c8erqtrsdzcve","chunk_label":"unnamed-chunk-15"},{"row":167,"row_count":1,"visible":true,"expansion_state":0,"options":{"engine":"r","label":"unnamed-chunk-123"},"document_id":"9127FD84","chunk_id":"csv2txtzrozd7","chunk_label":"unnamed-chunk-16"},{"row":175,"row_count":1,"visible":true,"expansion_state":0,"options":{"engine":"r","label":"unnamed-chunk-134"},"document_id":"9127FD84","chunk_id":"c36yh7bxi31l4","chunk_label":"unnamed-chunk-17"},{"row":180,"row_count":1,"visible":true,"expansion_state":0,"options":{"engine":"r","label":"unnamed-chunk-129"},"document_id":"9127FD84","chunk_id":"cggy2h0yo2o4c","chunk_label":"unnamed-chunk-18"}],"doc_write_time":1671676281,"chunk_rendered_width":683}